journyio/__init__.py
journyio/account_identified.py
journyio/client.py
journyio/events.py
journyio/httpclient.py
journyio/results.py
journyio/user_identified.py
journyio/utils.py
journyio/version.py
tests/__init__.py
tests/test_account_identified.py
tests/test_client.py
tests/test_events.py
tests/test_httpclient.py
tests/test_results.py
tests/test_user_identified.py
tests/test_utils.py
journyio_sdk-2.3.1.dist-info/LICENSE
journyio_sdk-2.3.1.dist-info/METADATA
journyio_sdk-2.3.1.dist-info/WHEEL
journyio_sdk-2.3.1.dist-info/top_level.txt
journyio_sdk-2.3.1.dist-info/RECORD
