Metadata-Version: 2.1
Name: journyio-sdk
Version: 2.3.1
Summary: This is the official Python SDK for journy.io.
Home-page: https://github.com/journy-io/python-sdk
Author: journy.io
Author-email: hi@journy.io
License: UNKNOWN
Platform: UNKNOWN
Classifier: Programming Language :: Python :: 3
Classifier: License :: OSI Approved :: MIT License
Classifier: Operating System :: OS Independent
Requires-Python: >=3.6
License-File: LICENSE
Requires-Dist: requests
